drdictaphone_shared/config_path.py
drdictaphone_shared/rpc.py
drdictaphone_shared/status_line.py
drdictaphone_shared-0.9.3.dist-info/LICENSE
drdictaphone_shared-0.9.3.dist-info/METADATA
drdictaphone_shared-0.9.3.dist-info/WHEEL
drdictaphone_shared-0.9.3.dist-info/RECORD
