Metadata-Version: 2.1
Name: drdictaphone-shared
Version: 0.9.3
Summary: Dictation app for the terminal and Neovim
License: LICENSE
Author: Ole Kliemann
Author-email: mail@olekliemann.de
Requires-Python: >=3.6
Classifier: Development Status :: 4 - Beta
Classifier: Intended Audience :: Developers
Classifier: Intended Audience :: End Users/Desktop
Classifier: License :: OSI Approved :: Apache Software License
Classifier: License :: Other/Proprietary License
Classifier: Operating System :: OS Independent
Classifier: Programming Language :: Python :: 3
Classifier: Programming Language :: Python :: 3.6
Classifier: Programming Language :: Python :: 3.7
Classifier: Programming Language :: Python :: 3.8
Classifier: Programming Language :: Python :: 3.9
Classifier: Programming Language :: Python :: 3.10
Classifier: Programming Language :: Python :: 3.11
Classifier: Programming Language :: Python :: 3.12
Classifier: Topic :: Text Processing
Requires-Dist: MrEventLoop (>=0.6.2)
